plugins/__init__.py
plugins/InformaticaPlugin/__init__.py
plugins/InformaticaPlugin/blueprints/__init__.py
plugins/InformaticaPlugin/blueprints/trigger_dag.py
plugins/InformaticaPlugin/operators/__init__.py
plugins/InformaticaPlugin/operators/execute_mapping.py
plugins/InformaticaPlugin/operators/execute_profile.py
plugins/InformaticaPlugin/operators/execute_scorecard.py
plugins/InformaticaPlugin/operators/execute_workflow.py
plugins/informatica_plugin/__init__.py
plugins/informatica_plugin/blueprints/__init__.py
plugins/informatica_plugin/blueprints/trigger_dag.py
plugins/informatica_plugin/operators/__init__.py
plugins/informatica_plugin/operators/execute_mapping.py
plugins/informatica_plugin/operators/execute_profile.py
plugins/informatica_plugin/operators/execute_scorecard.py
informatica_airflow_plugin-0.5.10.dist-info/LICENSE
informatica_airflow_plugin-0.5.10.dist-info/METADATA
informatica_airflow_plugin-0.5.10.dist-info/WHEEL
informatica_airflow_plugin-0.5.10.dist-info/top_level.txt
informatica_airflow_plugin-0.5.10.dist-info/RECORD
