Metadata-Version: 2.1
Name: informatica-airflow-plugin
Version: 0.5.10
Summary: Airflow Plugin for Informatica Platform
Home-page: https://github.com/jacbeekers/informatica-airflow-plugin
Author: Jac. Beekers
Author-email: beekersjac@gmail.com
License: UNKNOWN
Platform: UNKNOWN
Classifier: Programming Language :: Python :: 3
Classifier: License :: OSI Approved :: MIT License
Classifier: Operating System :: OS Independent
Requires-Python: >=3.6
Requires-Dist: devops-informatica-tools
